tds2stac/__init__.py
tds2stac/_version.py
tds2stac/assets.py
tds2stac/creator.py
tds2stac/extra_metadata.json
tds2stac/harvester.py
tds2stac/logger.py
tds2stac/py.typed
tds2stac/tag_config.json
tds2stac/tds2stac.py
tds2stac/thumbnails.py
tds2stac/utils.py
tds2stac/analysers/__init__.py
tds2stac/analysers/existence_validator.py
tds2stac/analysers/nested_collections.py
tds2stac/analysers/properties_verifier.py
tds2stac/analysers/recognizer.py
tds2stac/dimensions/__init__.py
tds2stac/dimensions/spatial.py
tds2stac/dimensions/temporal.py
tds2stac/extensions/__init__.py
tds2stac/extensions/common_metadata.py
tds2stac/extensions/datacube.py
tds2stac/extensions/extra_metadata.py
tds2stac/statics/__init__.py
tds2stac/statics/constants.py
tds2stac/webservices/__init__.py
tds2stac/webservices/core.py
tds2stac-3.1.25.dist-info/CC-BY-4.0.txt
tds2stac-3.1.25.dist-info/CC0-1.0.txt
tds2stac-3.1.25.dist-info/EUPL-1.2.txt
tds2stac-3.1.25.dist-info/METADATA
tds2stac-3.1.25.dist-info/WHEEL
tds2stac-3.1.25.dist-info/top_level.txt
tds2stac-3.1.25.dist-info/RECORD
