Metadata-Version: 2.1
Name: tds2stac
Version: 3.1.25
Summary: TDS2STAC
Author-email: Mostafa Hadizadeh <mostafa.hadizadeh@kit.edu>
Maintainer-email: Mostafa Hadizadeh <mostafa.hadizadeh@kit.edu>
License: EUPL-1.2
Project-URL: Homepage, https://codebase.helmholtz.cloud/cat4kit/ds2stac/tds2stac
Project-URL: Documentation, https://tds2stac.readthedocs.io/en/latest/
Project-URL: Source, https://codebase.helmholtz.cloud/cat4kit/ds2stac/tds2stac
Project-URL: Tracker, https://codebase.helmholtz.cloud/cat4kit/ds2stac/tds2stac/issues/
Classifier: Intended Audience :: Developers
Classifier: License :: OSI Approved :: European Union Public Licence 1.2 (EUPL 1.2)
Classifier: Operating System :: OS Independent
Classifier: Programming Language :: Python
Classifier: Programming Language :: Python :: 3
Classifier: Programming Language :: Python :: 3 :: Only
Classifier: Programming Language :: Python :: 3.9
Classifier: Programming Language :: Python :: 3.10
Classifier: Typing :: Typed
Requires-Python: >=3.9
License-File: LICENSES/CC-BY-4.0.txt
License-File: LICENSES/CC0-1.0.txt
License-File: LICENSES/EUPL-1.2.txt
Requires-Dist: urllib3 ==1.26.6
Requires-Dist: versioneer ==0.29
Requires-Dist: pystac ==1.8.3
Requires-Dist: lxml ==4.9.3
Requires-Dist: requests ==2.31.0
Requires-Dist: pytz ==2023.3
Requires-Dist: tqdm ==4.66.1
Requires-Dist: shapely ==2.0.4
Requires-Dist: pypgstac ==0.7.10
Requires-Dist: psycopg ==3.1.10
Requires-Dist: psycopg-pool ==3.1.7
Provides-Extra: dev
Requires-Dist: tds2stac[testsite] ; extra == 'dev'
Requires-Dist: tds2stac[docs] ; extra == 'dev'
Requires-Dist: PyYAML ; extra == 'dev'
Requires-Dist: types-PyYAML ; extra == 'dev'
Provides-Extra: docs
Requires-Dist: autodocsumm ; extra == 'docs'
Requires-Dist: sphinx-rtd-theme ; extra == 'docs'
Requires-Dist: hereon-netcdf-sphinxext ; extra == 'docs'
Requires-Dist: sphinx-design ; extra == 'docs'
Requires-Dist: myst-parser ; extra == 'docs'
Provides-Extra: testsite
Requires-Dist: tox ; extra == 'testsite'
Requires-Dist: tox-docker ; extra == 'testsite'
Requires-Dist: isort ==5.12.0 ; extra == 'testsite'
Requires-Dist: black ==23.1.0 ; extra == 'testsite'
Requires-Dist: blackdoc ==0.3.8 ; extra == 'testsite'
Requires-Dist: flake8 ==6.0.0 ; extra == 'testsite'
Requires-Dist: pre-commit ; extra == 'testsite'
Requires-Dist: mypy ; extra == 'testsite'
Requires-Dist: pytest-cov ; extra == 'testsite'
Requires-Dist: reuse ; extra == 'testsite'
Requires-Dist: cffconvert ; extra == 'testsite'
Requires-Dist: types-pytz ; extra == 'testsite'
Requires-Dist: types-requests ; extra == 'testsite'
Requires-Dist: types-python-dateutil ; extra == 'testsite'
